MANIFEST.in
README.md
phablet-demo-setup
phablet-dev-bootstrap
phablet-flash
phablet-network-setup
phablet-test-run
repo
setup.py
phablet_tools.egg-info/PKG-INFO
phablet_tools.egg-info/SOURCES.txt
phablet_tools.egg-info/dependency_links.txt
phablet_tools.egg-info/requires.txt
phablet_tools.egg-info/top_level.txt
phabletutils/__init__.py
phabletutils/cdimage.py
phabletutils/device.py
phabletutils/downloads.py
phabletutils/environment.py
phabletutils/settings.py
phabletutils/ubuntuimage.py