Metadata-Version: 1.0
Name: phablet-tools
Version: 0.1.2013080603
Summary: Scripts to deploy Ubuntu on mobile devices
Home-page: https://github.com/mikeshi80/phablet-tools
Author: Mike Shi
Author-email: mikeshi80@gmail.com
License: GPLv3
Platform: Windows
Platform: Linux
Platform: Mac OSX
